bmi/__init__.py
bmi/api.py
bmi/runner.py
bmi/wrapper.py
bmi_python-0.3.0.dist-info/DESCRIPTION.rst
bmi_python-0.3.0.dist-info/METADATA
bmi_python-0.3.0.dist-info/RECORD
bmi_python-0.3.0.dist-info/WHEEL
bmi_python-0.3.0.dist-info/entry_points.txt
bmi_python-0.3.0.dist-info/metadata.json
bmi_python-0.3.0.dist-info/top_level.txt
