Metadata-Version: 2.0
Name: bmi-python
Version: 0.3.0
Summary: Python wrapper for BMI libraries
Home-page: https://github.com/openearth/bmi-python
Author: Fedor Baart
Author-email: fedor.baart@deltares.nl
License: GPLv3+
Keywords: hydrodynamic,simulation,flooding,BMI
Platform: UNKNOWN
Classifier: Intended Audience :: Science/Research
Classifier: License :: OSI Approved :: GNU General Public License v3 or later (GPLv3+)
Classifier: Topic :: Scientific/Engineering
Classifier: Topic :: Software Development :: Libraries
Classifier: Programming Language :: Python :: 2
Classifier: Programming Language :: Python :: 2.7
Classifier: Programming Language :: Python :: 3
Classifier: Programming Language :: Python :: 3.5
Provides-Extra: test
Requires-Dist: setuptools
Requires-Dist: numpy
Requires-Dist: docopts
Requires-Dist: six
Provides-Extra: test
Requires-Dist: nose; extra == 'test'
Requires-Dist: mock; extra == 'test'
Requires-Dist: coverage; extra == 'test'
